{"box_data": [{"position": {"minX": 271.5, "minY": 193.75, "maxX": 425.5, "maxY": 369.25}, "class_id": 6, "box_caption": "yogurt 0.509", "scores": {"class_score": 0.5087890625}, "domain": "pixel"}, {"position": {"minX": 347.0, "minY": 171.0, "maxX": 511.0, "maxY": 343.5}, "class_id": 22, "box_caption": "medaglioni_di_carne 0.343", "scores": {"class_score": 0.3427734375}, "domain": "pixel"}, {"position": {"minX": 349.0, "minY": 168.125, "maxX": 509.0, "maxY": 347.0}, "class_id": 29, "box_caption": "polpette_di_carne 0.276", "scores": {"class_score": 0.275634765625}, "domain": "pixel"}, {"position": {"minX": 271.5, "minY": 193.75, "maxX": 425.5, "maxY": 369.25}, "class_id": 8, "box_caption": "spinaci 0.261", "scores": {"class_score": 0.2607421875}, "domain": "pixel"}, {"position": {"minX": 266.75, "minY": 200.25, "maxX": 437.25, "maxY": 359.75}, "class_id": 15, "box_caption": "lasagna_alla_bolognese 0.143", "scores": {"class_score": 0.1431884765625}, "domain": "pixel"}, {"position": {"minX": 266.75, "minY": 200.25, "maxX": 437.25, "maxY": 359.75}, "class_id": 39, "box_caption": "piselli 0.101", "scores": {"class_score": 0.10107421875}, "domain": "pixel"}, {"position": {"minX": 348.0, "minY": 180.125, "maxX": 499.0, "maxY": 343.0}, "class_id": 8, "box_caption": "spinaci 0.095", "scores": {"class_score": 0.09527587890625}, "domain": "pixel"}, {"position": {"minX": 350.75, "minY": 170.75, "maxX": 509.25, "maxY": 346.25}, "class_id": 45, "box_caption": "bruscitt 0.092", "scores": {"class_score": 0.09228515625}, "domain": "pixel"}, {"position": {"minX": 350.5, "minY": 184.25, "maxX": 510.5, "maxY": 336.75}, "class_id": 23, "box_caption": "torta_salata_spinaci_e_ricotta 0.084", "scores": {"class_score": 0.0838623046875}, "domain": "pixel"}, {"position": {"minX": 346.5, "minY": 169.75, "maxX": 511.0, "maxY": 348.25}, "class_id": 3, "box_caption": "patate/pure 0.075", "scores": {"class_score": 0.0751953125}, "domain": "pixel"}, {"position": {"minX": 271.5, "minY": 193.75, "maxX": 425.5, "maxY": 369.25}, "class_id": 26, "box_caption": "torta_salata_rustica_(zucchine) 0.067", "scores": {"class_score": 0.0667724609375}, "domain": "pixel"}, {"position": {"minX": 347.0, "minY": 171.0, "maxX": 511.0, "maxY": 343.5}, "class_id": 2, "box_caption": "carote 0.064", "scores": {"class_score": 0.063720703125}, "domain": "pixel"}, {"position": {"minX": 348.75, "minY": 179.5, "maxX": 510.25, "maxY": 338.5}, "class_id": 32, "box_caption": "orecchiette_(ragu) 0.063", "scores": {"class_score": 0.06268310546875}, "domain": "pixel"}, {"position": {"minX": 348.75, "minY": 179.5, "maxX": 510.25, "maxY": 338.5}, "class_id": 47, "box_caption": "pasta_e_fagioli 0.060", "scores": {"class_score": 0.059600830078125}, "domain": "pixel"}, {"position": {"minX": 346.5, "minY": 169.75, "maxX": 511.0, "maxY": 348.25}, "class_id": 42, "box_caption": "banane 0.056", "scores": {"class_score": 0.056427001953125}, "domain": "pixel"}, {"position": {"minX": 348.75, "minY": 179.5, "maxX": 510.25, "maxY": 338.5}, "class_id": 14, "box_caption": "zucchine_umido 0.054", "scores": {"class_score": 0.054046630859375}, "domain": "pixel"}, {"position": {"minX": 350.5, "minY": 184.25, "maxX": 510.5, "maxY": 336.75}, "class_id": 48, "box_caption": "pasta_sugo 0.052", "scores": {"class_score": 0.051910400390625}, "domain": "pixel"}, {"position": {"minX": 348.0, "minY": 180.125, "maxX": 499.0, "maxY": 343.0}, "class_id": 6, "box_caption": "yogurt 0.044", "scores": {"class_score": 0.04449462890625}, "domain": "pixel"}, {"position": {"minX": 266.25, "minY": 203.75, "maxX": 437.25, "maxY": 357.75}, "class_id": 32, "box_caption": "orecchiette_(ragu) 0.040", "scores": {"class_score": 0.039886474609375}, "domain": "pixel"}, {"position": {"minX": 346.0, "minY": 172.25, "maxX": 512.5, "maxY": 345.75}, "class_id": 40, "box_caption": "torta_salata_3 0.034", "scores": {"class_score": 0.03363037109375}, "domain": "pixel"}, {"position": {"minX": 347.0, "minY": 176.25, "maxX": 511.5, "maxY": 342.25}, "class_id": 27, "box_caption": "insalata_mista 0.029", "scores": {"class_score": 0.028594970703125}, "domain": "pixel"}, {"position": {"minX": 350.75, "minY": 170.75, "maxX": 509.25, "maxY": 346.25}, "class_id": 44, "box_caption": "pesce_2_(filetto) 0.028", "scores": {"class_score": 0.0281829833984375}, "domain": "pixel"}, {"position": {"minX": 346.0, "minY": 172.25, "maxX": 512.5, "maxY": 345.75}, "class_id": 9, "box_caption": "scaloppine 0.027", "scores": {"class_score": 0.0266571044921875}, "domain": "pixel"}, {"position": {"minX": 350.5, "minY": 171.25, "maxX": 512.5, "maxY": 345.25}, "class_id": 50, "box_caption": "stinco_di_maiale 0.022", "scores": {"class_score": 0.021697998046875}, "domain": "pixel"}, {"position": {"minX": 348.75, "minY": 179.5, "maxX": 510.25, "maxY": 338.5}, "class_id": 38, "box_caption": "pasta_tonno_e_piselli 0.020", "scores": {"class_score": 0.0201263427734375}, "domain": "pixel"}, {"position": {"minX": 348.75, "minY": 179.5, "maxX": 510.25, "maxY": 338.5}, "class_id": 56, "box_caption": "zucchine_impanate 0.018", "scores": {"class_score": 0.017608642578125}, "domain": "pixel"}, {"position": {"minX": 346.0, "minY": 172.25, "maxX": 512.5, "maxY": 345.75}, "class_id": 28, "box_caption": "pasta_mare_e_monti 0.017", "scores": {"class_score": 0.01727294921875}, "domain": "pixel"}, {"position": {"minX": 346.0, "minY": 175.875, "maxX": 512.0, "maxY": 336.5}, "class_id": 61, "box_caption": "cibo_bianco_non_identificato 0.017", "scores": {"class_score": 0.0169677734375}, "domain": "pixel"}, {"position": {"minX": 347.0, "minY": 176.25, "maxX": 511.5, "maxY": 342.25}, "class_id": 20, "box_caption": "arrosto 0.017", "scores": {"class_score": 0.016937255859375}, "domain": "pixel"}, {"position": {"minX": 346.0, "minY": 175.875, "maxX": 512.0, "maxY": 336.5}, "class_id": 26, "box_caption": "torta_salata_rustica_(zucchine) 0.016", "scores": {"class_score": 0.015777587890625}, "domain": "pixel"}, {"position": {"minX": 353.0, "minY": 174.0, "maxX": 492.5, "maxY": 349.0}, "class_id": 39, "box_caption": "piselli 0.013", "scores": {"class_score": 0.01346588134765625}, "domain": "pixel"}, {"position": {"minX": 347.0, "minY": 176.25, "maxX": 511.5, "maxY": 342.25}, "class_id": 36, "box_caption": "pasta_tonno 0.013", "scores": {"class_score": 0.013214111328125}, "domain": "pixel"}, {"position": {"minX": 309.25, "minY": 273.25, "maxX": 429.25, "maxY": 371.25}, "class_id": 6, "box_caption": "yogurt 0.013", "scores": {"class_score": 0.01291656494140625}, "domain": "pixel"}, {"position": {"minX": 262.0, "minY": 194.0, "maxX": 440.0, "maxY": 369.0}, "class_id": 18, "box_caption": "patatine_fritte 0.013", "scores": {"class_score": 0.01268768310546875}, "domain": "pixel"}, {"position": {"minX": 272.25, "minY": 203.5, "maxX": 438.75, "maxY": 372.5}, "class_id": 33, "box_caption": "pizzoccheri 0.012", "scores": {"class_score": 0.012176513671875}, "domain": "pixel"}, {"position": {"minX": 255.5, "minY": 208.75, "maxX": 410.5, "maxY": 328.25}, "class_id": 6, "box_caption": "yogurt 0.012", "scores": {"class_score": 0.0115966796875}, "domain": "pixel"}, {"position": {"minX": 347.0, "minY": 176.25, "maxX": 511.5, "maxY": 342.25}, "class_id": 11, "box_caption": "pasta_sugo_vegetariano 0.011", "scores": {"class_score": 0.01146697998046875}, "domain": "pixel"}, {"position": {"minX": 314.0, "minY": 237.25, "maxX": 452.5, "maxY": 369.25}, "class_id": 6, "box_caption": "yogurt 0.011", "scores": {"class_score": 0.01120758056640625}, "domain": "pixel"}, {"position": {"minX": 350.5, "minY": 184.25, "maxX": 510.5, "maxY": 336.75}, "class_id": 31, "box_caption": "pasta_ricotta_e_salsiccia 0.011", "scores": {"class_score": 0.0109100341796875}, "domain": "pixel"}, {"position": {"minX": 350.5, "minY": 184.25, "maxX": 510.5, "maxY": 336.75}, "class_id": 34, "box_caption": "finocchi_gratinati 0.010", "scores": {"class_score": 0.0097503662109375}, "domain": "pixel"}, {"position": {"minX": 347.0, "minY": 176.25, "maxX": 511.5, "maxY": 342.25}, "class_id": 37, "box_caption": "riso_sugo 0.010", "scores": {"class_score": 0.0097198486328125}, "domain": "pixel"}, {"position": {"minX": 347.0, "minY": 171.0, "maxX": 511.0, "maxY": 343.5}, "class_id": 57, "box_caption": "pesce_(filetto) 0.009", "scores": {"class_score": 0.0093994140625}, "domain": "pixel"}, {"position": {"minX": 347.0, "minY": 176.25, "maxX": 511.5, "maxY": 342.25}, "class_id": 17, "box_caption": "pasta_sugo_pesce 0.009", "scores": {"class_score": 0.00913238525390625}, "domain": "pixel"}, {"position": {"minX": 262.75, "minY": 187.0, "maxX": 364.75, "maxY": 319.5}, "class_id": 6, "box_caption": "yogurt 0.008", "scores": {"class_score": 0.00823974609375}, "domain": "pixel"}, {"position": {"minX": 481.5, "minY": 168.625, "maxX": 587.5, "maxY": 260.5}, "class_id": 9, "box_caption": "scaloppine 0.008", "scores": {"class_score": 0.0077056884765625}, "domain": "pixel"}, {"position": {"minX": 309.25, "minY": 273.25, "maxX": 429.25, "maxY": 371.25}, "class_id": 15, "box_caption": "lasagna_alla_bolognese 0.007", "scores": {"class_score": 0.00720977783203125}, "domain": "pixel"}, {"position": {"minX": 346.0, "minY": 172.25, "maxX": 512.5, "maxY": 345.75}, "class_id": 43, "box_caption": "salmone_(da_menu_sembra_spada_in_realta) 0.007", "scores": {"class_score": 0.0069732666015625}, "domain": "pixel"}, {"position": {"minX": 349.0, "minY": 168.125, "maxX": 509.0, "maxY": 347.0}, "class_id": 58, "box_caption": "torta_crema_2 0.007", "scores": {"class_score": 0.00693511962890625}, "domain": "pixel"}, {"position": {"minX": 266.25, "minY": 203.75, "maxX": 437.25, "maxY": 357.75}, "class_id": 29, "box_caption": "polpette_di_carne 0.007", "scores": {"class_score": 0.00687408447265625}, "domain": "pixel"}, {"position": {"minX": 347.0, "minY": 175.25, "maxX": 513.0, "maxY": 336.75}, "class_id": 33, "box_caption": "pizzoccheri 0.006", "scores": {"class_score": 0.00620269775390625}, "domain": "pixel"}, {"position": {"minX": 348.75, "minY": 179.5, "maxX": 510.25, "maxY": 338.5}, "class_id": 46, "box_caption": "guazzetto_di_calamari 0.006", "scores": {"class_score": 0.006099700927734375}, "domain": "pixel"}, {"position": {"minX": 264.5, "minY": 200.0, "maxX": 431.5, "maxY": 342.5}, "class_id": 55, "box_caption": "merluzzo_alle_olive 0.006", "scores": {"class_score": 0.005615234375}, "domain": "pixel"}, {"position": {"minX": 269.75, "minY": 197.875, "maxX": 439.75, "maxY": 373.5}, "class_id": 52, "box_caption": "finocchi_in_umido 0.005", "scores": {"class_score": 0.00543212890625}, "domain": "pixel"}, {"position": {"minX": 265.75, "minY": 199.0, "maxX": 436.75, "maxY": 363.5}, "class_id": 36, "box_caption": "pasta_tonno 0.005", "scores": {"class_score": 0.005191802978515625}, "domain": "pixel"}, {"position": {"minX": 348.75, "minY": 179.5, "maxX": 510.25, "maxY": 338.5}, "class_id": 49, "box_caption": "arrosto_di_vitello 0.005", "scores": {"class_score": 0.00518035888671875}, "domain": "pixel"}, {"position": {"minX": 271.5, "minY": 197.25, "maxX": 431.5, "maxY": 347.75}, "class_id": 22, "box_caption": "medaglioni_di_carne 0.004", "scores": {"class_score": 0.004241943359375}, "domain": "pixel"}, {"position": {"minX": 264.5, "minY": 200.0, "maxX": 431.5, "maxY": 342.5}, "class_id": 61, "box_caption": "cibo_bianco_non_identificato 0.004", "scores": {"class_score": 0.004032135009765625}, "domain": "pixel"}, {"position": {"minX": 266.75, "minY": 200.25, "maxX": 437.25, "maxY": 359.75}, "class_id": 30, "box_caption": "pasta_pancetta_e_zucchine 0.004", "scores": {"class_score": 0.00400543212890625}, "domain": "pixel"}, {"position": {"minX": 266.25, "minY": 203.75, "maxX": 437.25, "maxY": 357.75}, "class_id": 34, "box_caption": "finocchi_gratinati 0.004", "scores": {"class_score": 0.003932952880859375}, "domain": "pixel"}, {"position": {"minX": 265.75, "minY": 199.0, "maxX": 436.75, "maxY": 363.5}, "class_id": 44, "box_caption": "pesce_2_(filetto) 0.004", "scores": {"class_score": 0.003910064697265625}, "domain": "pixel"}, {"position": {"minX": 323.25, "minY": 284.5, "maxX": 443.25, "maxY": 375.5}, "class_id": 4, "box_caption": "cotoletta 0.004", "scores": {"class_score": 0.003696441650390625}, "domain": "pixel"}, {"position": {"minX": 350.5, "minY": 171.25, "maxX": 512.5, "maxY": 345.25}, "class_id": 19, "box_caption": "pasta_cozze_e_vongole 0.004", "scores": {"class_score": 0.0036334991455078125}, "domain": "pixel"}, {"position": {"minX": 314.0, "minY": 237.25, "maxX": 452.5, "maxY": 369.25}, "class_id": 8, "box_caption": "spinaci 0.003", "scores": {"class_score": 0.0034656524658203125}, "domain": "pixel"}, {"position": {"minX": 262.0, "minY": 194.0, "maxX": 440.0, "maxY": 369.0}, "class_id": 24, "box_caption": "pasta_zafferano_e_piselli 0.003", "scores": {"class_score": 0.0034351348876953125}, "domain": "pixel"}, {"position": {"minX": 345.5, "minY": 178.0, "maxX": 513.5, "maxY": 343.5}, "class_id": 10, "box_caption": "pizza 0.003", "scores": {"class_score": 0.0034313201904296875}, "domain": "pixel"}, {"position": {"minX": 295.75, "minY": 203.0, "maxX": 406.25, "maxY": 339.0}, "class_id": 8, "box_caption": "spinaci 0.003", "scores": {"class_score": 0.003261566162109375}, "domain": "pixel"}, {"position": {"minX": 346.0, "minY": 172.25, "maxX": 512.5, "maxY": 345.75}, "class_id": 25, "box_caption": "patate/pure_prosciutto 0.003", "scores": {"class_score": 0.0032062530517578125}, "domain": "pixel"}, {"position": {"minX": 290.0, "minY": 199.25, "maxX": 403.0, "maxY": 342.75}, "class_id": 15, "box_caption": "lasagna_alla_bolognese 0.003", "scores": {"class_score": 0.003055572509765625}, "domain": "pixel"}, {"position": {"minX": 567.0, "minY": 244.5, "maxX": 594.0, "maxY": 277.5}, "class_id": 1, "box_caption": "mandarini 0.003", "scores": {"class_score": 0.0029926300048828125}, "domain": "pixel"}, {"position": {"minX": 269.75, "minY": 197.875, "maxX": 439.75, "maxY": 373.5}, "class_id": 62, "box_caption": "torta_crema 0.003", "scores": {"class_score": 0.0029621124267578125}, "domain": "pixel"}, {"position": {"minX": 481.5, "minY": 168.625, "maxX": 587.5, "maxY": 260.5}, "class_id": 41, "box_caption": "torta_salata_(alla_valdostana) 0.003", "scores": {"class_score": 0.0027103424072265625}, "domain": "pixel"}, {"position": {"minX": 262.5, "minY": 193.5, "maxX": 368.0, "maxY": 314.0}, "class_id": 8, "box_caption": "spinaci 0.003", "scores": {"class_score": 0.0027103424072265625}, "domain": "pixel"}, {"position": {"minX": 553.0, "minY": 240.0, "maxX": 612.0, "maxY": 294.0}, "class_id": 1, "box_caption": "mandarini 0.003", "scores": {"class_score": 0.0026454925537109375}, "domain": "pixel"}, {"position": {"minX": 266.25, "minY": 203.75, "maxX": 437.25, "maxY": 357.75}, "class_id": 11, "box_caption": "pasta_sugo_vegetariano 0.003", "scores": {"class_score": 0.002574920654296875}, "domain": "pixel"}, {"position": {"minX": 560.0, "minY": 251.375, "maxX": 601.0, "maxY": 284.5}, "class_id": 1, "box_caption": "mandarini 0.003", "scores": {"class_score": 0.0025043487548828125}, "domain": "pixel"}, {"position": {"minX": 348.0, "minY": 180.125, "maxX": 499.0, "maxY": 343.0}, "class_id": 15, "box_caption": "lasagna_alla_bolognese 0.002", "scores": {"class_score": 0.00246429443359375}, "domain": "pixel"}, {"position": {"minX": 266.25, "minY": 203.75, "maxX": 437.25, "maxY": 357.75}, "class_id": 38, "box_caption": "pasta_tonno_e_piselli 0.002", "scores": {"class_score": 0.0024280548095703125}, "domain": "pixel"}, {"position": {"minX": 271.5, "minY": 197.25, "maxX": 431.5, "maxY": 347.75}, "class_id": 48, "box_caption": "pasta_sugo 0.002", "scores": {"class_score": 0.0024242401123046875}, "domain": "pixel"}, {"position": {"minX": 323.25, "minY": 284.5, "maxX": 443.25, "maxY": 375.5}, "class_id": 52, "box_caption": "finocchi_in_umido 0.002", "scores": {"class_score": 0.0022945404052734375}, "domain": "pixel"}, {"position": {"minX": 432.5, "minY": 90.5, "maxX": 536.5, "maxY": 175.0}, "class_id": 10, "box_caption": "pizza 0.002", "scores": {"class_score": 0.002193450927734375}, "domain": "pixel"}, {"position": {"minX": 323.25, "minY": 284.5, "maxX": 443.25, "maxY": 375.5}, "class_id": 25, "box_caption": "patate/pure_prosciutto 0.002", "scores": {"class_score": 0.0021648406982421875}, "domain": "pixel"}, {"position": {"minX": 431.75, "minY": 79.3125, "maxX": 538.0, "maxY": 182.5}, "class_id": 18, "box_caption": "patatine_fritte 0.002", "scores": {"class_score": 0.00211334228515625}, "domain": "pixel"}, {"position": {"minX": 343.25, "minY": 174.0, "maxX": 515.0, "maxY": 338.0}, "class_id": 55, "box_caption": "merluzzo_alle_olive 0.002", "scores": {"class_score": 0.0020618438720703125}, "domain": "pixel"}, {"position": {"minX": 481.5, "minY": 168.625, "maxX": 587.5, "maxY": 260.5}, "class_id": 19, "box_caption": "pasta_cozze_e_vongole 0.002", "scores": {"class_score": 0.0020236968994140625}, "domain": "pixel"}, {"position": {"minX": 562.0, "minY": 239.875, "maxX": 607.0, "maxY": 281.25}, "class_id": 1, "box_caption": "mandarini 0.002", "scores": {"class_score": 0.001979827880859375}, "domain": "pixel"}, {"position": {"minX": 314.0, "minY": 237.25, "maxX": 452.5, "maxY": 369.25}, "class_id": 15, "box_caption": "lasagna_alla_bolognese 0.002", "scores": {"class_score": 0.001953125}, "domain": "pixel"}, {"position": {"minX": 432.5, "minY": 90.5, "maxX": 536.5, "maxY": 175.0}, "class_id": 26, "box_caption": "torta_salata_rustica_(zucchine) 0.002", "scores": {"class_score": 0.0019092559814453125}, "domain": "pixel"}, {"position": {"minX": 266.25, "minY": 203.75, "maxX": 437.25, "maxY": 357.75}, "class_id": 31, "box_caption": "pasta_ricotta_e_salsiccia 0.002", "scores": {"class_score": 0.0018491744995117188}, "domain": "pixel"}, {"position": {"minX": 327.0, "minY": 285.0, "maxX": 438.0, "maxY": 373.5}, "class_id": 33, "box_caption": "pizzoccheri 0.002", "scores": {"class_score": 0.0017061233520507812}, "domain": "pixel"}, {"position": {"minX": 569.0, "minY": 256.25, "maxX": 598.0, "maxY": 282.25}, "class_id": 1, "box_caption": "mandarini 0.002", "scores": {"class_score": 0.0016756057739257812}, "domain": "pixel"}, {"position": {"minX": 319.0, "minY": 302.0, "maxX": 435.5, "maxY": 373.5}, "class_id": 18, "box_caption": "patatine_fritte 0.002", "scores": {"class_score": 0.0016756057739257812}, "domain": "pixel"}, {"position": {"minX": 262.75, "minY": 187.0, "maxX": 364.75, "maxY": 319.5}, "class_id": 15, "box_caption": "lasagna_alla_bolognese 0.002", "scores": {"class_score": 0.0016279220581054688}, "domain": "pixel"}, {"position": {"minX": 347.0, "minY": 176.25, "maxX": 511.5, "maxY": 342.25}, "class_id": 67, "box_caption": "minestra 0.002", "scores": {"class_score": 0.0015974044799804688}, "domain": "pixel"}, {"position": {"minX": 297.5, "minY": 191.125, "maxX": 413.5, "maxY": 317.25}, "class_id": 6, "box_caption": "yogurt 0.002", "scores": {"class_score": 0.0015716552734375}, "domain": "pixel"}, {"position": {"minX": 347.0, "minY": 175.25, "maxX": 513.0, "maxY": 336.75}, "class_id": 30, "box_caption": "pasta_pancetta_e_zucchine 0.001", "scores": {"class_score": 0.0014057159423828125}, "domain": "pixel"}, {"position": {"minX": 271.5, "minY": 193.75, "maxX": 425.5, "maxY": 369.25}, "class_id": 2, "box_caption": "carote 0.001", "scores": {"class_score": 0.0014009475708007812}, "domain": "pixel"}, {"position": {"minX": 481.5, "minY": 168.625, "maxX": 587.5, "maxY": 260.5}, "class_id": 28, "box_caption": "pasta_mare_e_monti 0.001", "scores": {"class_score": 0.0013980865478515625}, "domain": "pixel"}, {"position": {"minX": 481.5, "minY": 168.625, "maxX": 587.5, "maxY": 260.5}, "class_id": 3, "box_caption": "patate/pure 0.001", "scores": {"class_score": 0.0013523101806640625}, "domain": "pixel"}, {"position": {"minX": 255.5, "minY": 208.75, "maxX": 410.5, "maxY": 328.25}, "class_id": 26, "box_caption": "torta_salata_rustica_(zucchine) 0.001", "scores": {"class_score": 0.0012617111206054688}, "domain": "pixel"}, {"position": {"minX": 428.0, "minY": 80.0, "maxX": 546.5, "maxY": 203.75}, "class_id": 10, "box_caption": "pizza 0.001", "scores": {"class_score": 0.0012331008911132812}, "domain": "pixel"}, {"position": {"minX": 481.5, "minY": 168.625, "maxX": 587.5, "maxY": 260.5}, "class_id": 23, "box_caption": "torta_salata_spinaci_e_ricotta 0.001", "scores": {"class_score": 0.0012302398681640625}, "domain": "pixel"}, {"position": {"minX": 431.75, "minY": 79.3125, "maxX": 538.0, "maxY": 182.5}, "class_id": 6, "box_caption": "yogurt 0.001", "scores": {"class_score": 0.0012197494506835938}, "domain": "pixel"}, {"position": {"minX": 269.75, "minY": 197.875, "maxX": 439.75, "maxY": 373.5}, "class_id": 25, "box_caption": "patate/pure_prosciutto 0.001", "scores": {"class_score": 0.0011682510375976562}, "domain": "pixel"}, {"position": {"minX": 481.5, "minY": 168.625, "maxX": 587.5, "maxY": 260.5}, "class_id": 43, "box_caption": "salmone_(da_menu_sembra_spada_in_realta) 0.001", "scores": {"class_score": 0.001132965087890625}, "domain": "pixel"}, {"position": {"minX": 346.0, "minY": 172.25, "maxX": 512.5, "maxY": 345.75}, "class_id": 53, "box_caption": "pasta_bianco 0.001", "scores": {"class_score": 0.0011243820190429688}, "domain": "pixel"}, {"position": {"minX": 342.5, "minY": 165.25, "maxX": 471.0, "maxY": 277.25}, "class_id": 22, "box_caption": "medaglioni_di_carne 0.001", "scores": {"class_score": 0.0011157989501953125}, "domain": "pixel"}, {"position": {"minX": 485.25, "minY": 166.5, "maxX": 585.0, "maxY": 266.5}, "class_id": 22, "box_caption": "medaglioni_di_carne 0.001", "scores": {"class_score": 0.0011110305786132812}, "domain": "pixel"}, {"position": {"minX": 362.5, "minY": 190.0, "maxX": 473.0, "maxY": 331.5}, "class_id": 29, "box_caption": "polpette_di_carne 0.001", "scores": {"class_score": 0.0010967254638671875}, "domain": "pixel"}, {"position": {"minX": 427.0, "minY": 79.1875, "maxX": 531.0, "maxY": 184.25}, "class_id": 5, "box_caption": "fagiolini 0.001", "scores": {"class_score": 0.0010919570922851562}, "domain": "pixel"}, {"position": {"minX": 350.5, "minY": 171.25, "maxX": 512.5, "maxY": 345.25}, "class_id": 65, "box_caption": "crema_zucca_e_fagioli 0.001", "scores": {"class_score": 0.0010824203491210938}, "domain": "pixel"}, {"position": {"minX": 348.75, "minY": 179.5, "maxX": 510.25, "maxY": 338.5}, "class_id": 63, "box_caption": "passato_alla_piemontese 0.001", "scores": {"class_score": 0.0010585784912109375}, "domain": "pixel"}, {"position": {"minX": 353.0, "minY": 174.0, "maxX": 492.5, "maxY": 349.0}, "class_id": 52, "box_caption": "finocchi_in_umido 0.001", "scores": {"class_score": 0.0010385513305664062}, "domain": "pixel"}, {"position": {"minX": 309.25, "minY": 273.25, "maxX": 429.25, "maxY": 371.25}, "class_id": 8, "box_caption": "spinaci 0.001", "scores": {"class_score": 0.00103759765625}, "domain": "pixel"}, {"position": {"minX": 432.5, "minY": 90.5, "maxX": 536.5, "maxY": 175.0}, "class_id": 8, "box_caption": "spinaci 0.001", "scores": {"class_score": 0.0010290145874023438}, "domain": "pixel"}, {"position": {"minX": 255.5, "minY": 208.75, "maxX": 410.5, "maxY": 328.25}, "class_id": 33, "box_caption": "pizzoccheri 0.001", "scores": {"class_score": 0.0010156631469726562}, "domain": "pixel"}], "class_labels": {"0": "pane", "1": "mandarini", "2": "carote", "3": "patate/pure", "4": "cotoletta", "5": "fagiolini", "6": "yogurt", "7": "budino", "8": "spinaci", "9": "scaloppine", "10": "pizza", "11": "pasta_sugo_vegetariano", "12": "mele", "13": "pasta_pesto_besciamella_e_cornetti", "14": "zucchine_umido", "15": "lasagna_alla_bolognese", "16": "arancia", "17": "pasta_sugo_pesce", "18": "patatine_fritte", "19": "pasta_cozze_e_vongole", "20": "arrosto", "21": "riso_bianco", "22": "medaglioni_di_carne", "23": "torta_salata_spinaci_e_ricotta", "24": "pasta_zafferano_e_piselli", "25": "patate/pure_prosciutto", "26": "torta_salata_rustica_(zucchine)", "27": "insalata_mista", "28": "pasta_mare_e_monti", "29": "polpette_di_carne", "30": "pasta_pancetta_e_zucchine", "31": "pasta_ricotta_e_salsiccia", "32": "orecchiette_(ragu)", "33": "pizzoccheri", "34": "finocchi_gratinati", "35": "pere", "36": "pasta_tonno", "37": "riso_sugo", "38": "pasta_tonno_e_piselli", "39": "piselli", "40": "torta_salata_3", "41": "torta_salata_(alla_valdostana)", "42": "banane", "43": "salmone_(da_menu_sembra_spada_in_realta)", "44": "pesce_2_(filetto)", "45": "bruscitt", "46": "guazzetto_di_calamari", "47": "pasta_e_fagioli", "48": "pasta_sugo", "49": "arrosto_di_vitello", "50": "stinco_di_maiale", "51": "minestra_lombarda", "52": "finocchi_in_umido", "53": "pasta_bianco", "54": "cavolfiore", "55": "merluzzo_alle_olive", "56": "zucchine_impanate", "57": "pesce_(filetto)", "58": "torta_crema_2", "59": "roastbeef", "60": "rosbeef", "61": "cibo_bianco_non_identificato", "62": "torta_crema", "63": "passato_alla_piemontese", "64": "pasta_e_ceci", "65": "crema_zucca_e_fagioli", "66": "focaccia_bianca", "67": "minestra", "68": "torta_cioccolato_e_pere", "69": "torta_ananas", "70": "rucola", "71": "strudel"}}