{"box_data": [{"position": {"minX": 443.75, "minY": 50.6875, "maxX": 540.0, "maxY": 147.75}, "class_id": 7, "box_caption": "pudding 0.953", "scores": {"class_score": 0.953125}, "domain": "pixel"}, {"position": {"minX": 84.625, "minY": 59.53125, "maxX": 182.375, "maxY": 168.0}, "class_id": 0, "box_caption": "bread 0.953", "scores": {"class_score": 0.953125}, "domain": "pixel"}, {"position": {"minX": 374.75, "minY": 204.25, "maxX": 530.0, "maxY": 318.75}, "class_id": 3, "box_caption": "schnitzel 0.937", "scores": {"class_score": 0.93701171875}, "domain": "pixel"}, {"position": {"minX": 371.5, "minY": 292.25, "maxX": 524.5, "maxY": 388.25}, "class_id": 4, "box_caption": "potatoes/purees 0.863", "scores": {"class_score": 0.86279296875}, "domain": "pixel"}, {"position": {"minX": 98.8125, "minY": 193.75, "maxX": 286.5, "maxY": 395.75}, "class_id": 20, "box_caption": "pasta_mussels_and_clams 0.291", "scores": {"class_score": 0.291259765625}, "domain": "pixel"}, {"position": {"minX": 99.875, "minY": 199.25, "maxX": 280.0, "maxY": 394.25}, "class_id": 17, "box_caption": "pasta_with_fish_sauce 0.236", "scores": {"class_score": 0.2362060546875}, "domain": "pixel"}, {"position": {"minX": 98.5625, "minY": 197.25, "maxX": 282.75, "maxY": 395.75}, "class_id": 27, "box_caption": "pasta_mare_e_monti 0.220", "scores": {"class_score": 0.2200927734375}, "domain": "pixel"}, {"position": {"minX": 98.5625, "minY": 197.25, "maxX": 282.75, "maxY": 395.75}, "class_id": 11, "box_caption": "pasta_sugar_vegetarian 0.190", "scores": {"class_score": 0.190185546875}, "domain": "pixel"}, {"position": {"minX": 99.25, "minY": 197.0, "maxX": 281.0, "maxY": 389.0}, "class_id": 31, "box_caption": "ricotta_and_sausage_pasta 0.182", "scores": {"class_score": 0.18212890625}, "domain": "pixel"}, {"position": {"minX": 101.0625, "minY": 202.625, "maxX": 281.75, "maxY": 390.5}, "class_id": 36, "box_caption": "tuna_pasta 0.091", "scores": {"class_score": 0.09124755859375}, "domain": "pixel"}, {"position": {"minX": 438.0, "minY": 50.25, "maxX": 544.0, "maxY": 152.375}, "class_id": 8, "box_caption": "spinach 0.044", "scores": {"class_score": 0.04400634765625}, "domain": "pixel"}, {"position": {"minX": 98.5625, "minY": 197.25, "maxX": 282.75, "maxY": 395.75}, "class_id": 38, "box_caption": "tuna_and_peas_pasta 0.035", "scores": {"class_score": 0.03533935546875}, "domain": "pixel"}, {"position": {"minX": 100.25, "minY": 200.625, "maxX": 283.25, "maxY": 389.5}, "class_id": 34, "box_caption": "orecchiette_ragu 0.020", "scores": {"class_score": 0.0196685791015625}, "domain": "pixel"}, {"position": {"minX": 443.5, "minY": 51.8125, "maxX": 541.5, "maxY": 144.5}, "class_id": 0, "box_caption": "bread 0.018", "scores": {"class_score": 0.0181121826171875}, "domain": "pixel"}, {"position": {"minX": 376.75, "minY": 289.75, "maxX": 517.0, "maxY": 390.75}, "class_id": 25, "box_caption": "potatoes/pure_ham 0.018", "scores": {"class_score": 0.0180206298828125}, "domain": "pixel"}, {"position": {"minX": 368.5, "minY": 208.75, "maxX": 533.0, "maxY": 315.25}, "class_id": 1, "box_caption": "tangerines 0.017", "scores": {"class_score": 0.0166473388671875}, "domain": "pixel"}, {"position": {"minX": 376.75, "minY": 289.75, "maxX": 517.0, "maxY": 390.75}, "class_id": 19, "box_caption": "roast 0.013", "scores": {"class_score": 0.0125885009765625}, "domain": "pixel"}, {"position": {"minX": 375.25, "minY": 203.25, "maxX": 532.0, "maxY": 320.25}, "class_id": 2, "box_caption": "carrots 0.012", "scores": {"class_score": 0.01171112060546875}, "domain": "pixel"}, {"position": {"minX": 376.0, "minY": 203.375, "maxX": 528.0, "maxY": 319.5}, "class_id": 28, "box_caption": "meatballs 0.012", "scores": {"class_score": 0.011505126953125}, "domain": "pixel"}, {"position": {"minX": 443.75, "minY": 50.6875, "maxX": 540.0, "maxY": 147.75}, "class_id": 20, "box_caption": "pasta_mussels_and_clams 0.011", "scores": {"class_score": 0.0113067626953125}, "domain": "pixel"}, {"position": {"minX": 373.5, "minY": 209.5, "maxX": 530.5, "maxY": 310.5}, "class_id": 47, "box_caption": "bruscitt 0.009", "scores": {"class_score": 0.008575439453125}, "domain": "pixel"}, {"position": {"minX": 443.75, "minY": 50.6875, "maxX": 540.0, "maxY": 147.75}, "class_id": 27, "box_caption": "pasta_mare_e_monti 0.008", "scores": {"class_score": 0.008331298828125}, "domain": "pixel"}, {"position": {"minX": 375.0, "minY": 213.0, "maxX": 530.5, "maxY": 308.5}, "class_id": 23, "box_caption": "meat_medallions 0.008", "scores": {"class_score": 0.007534027099609375}, "domain": "pixel"}, {"position": {"minX": 372.75, "minY": 211.5, "maxX": 530.0, "maxY": 310.0}, "class_id": 49, "box_caption": "pasta_and_beans 0.007", "scores": {"class_score": 0.006847381591796875}, "domain": "pixel"}, {"position": {"minX": 372.0, "minY": 294.0, "maxX": 523.0, "maxY": 389.5}, "class_id": 15, "box_caption": "moist_courgettes 0.006", "scores": {"class_score": 0.00617218017578125}, "domain": "pixel"}, {"position": {"minX": 371.25, "minY": 207.25, "maxX": 534.0, "maxY": 315.75}, "class_id": 19, "box_caption": "roast 0.006", "scores": {"class_score": 0.005840301513671875}, "domain": "pixel"}, {"position": {"minX": 98.5625, "minY": 197.25, "maxX": 282.75, "maxY": 395.75}, "class_id": 46, "box_caption": "pasta_sauce 0.006", "scores": {"class_score": 0.0056304931640625}, "domain": "pixel"}, {"position": {"minX": 376.75, "minY": 289.75, "maxX": 517.0, "maxY": 390.75}, "class_id": 52, "box_caption": "stewed_fennel 0.006", "scores": {"class_score": 0.005596160888671875}, "domain": "pixel"}, {"position": {"minX": 443.5, "minY": 50.71875, "maxX": 540.0, "maxY": 148.875}, "class_id": 12, "box_caption": "apples 0.005", "scores": {"class_score": 0.005359649658203125}, "domain": "pixel"}, {"position": {"minX": 377.25, "minY": 287.0, "maxX": 517.5, "maxY": 393.0}, "class_id": 8, "box_caption": "spinach 0.005", "scores": {"class_score": 0.004779815673828125}, "domain": "pixel"}, {"position": {"minX": 375.25, "minY": 203.25, "maxX": 532.0, "maxY": 320.25}, "class_id": 16, "box_caption": "orange 0.005", "scores": {"class_score": 0.004619598388671875}, "domain": "pixel"}, {"position": {"minX": 377.0, "minY": 206.0, "maxX": 528.0, "maxY": 315.0}, "class_id": 0, "box_caption": "bread 0.004", "scores": {"class_score": 0.0039520263671875}, "domain": "pixel"}, {"position": {"minX": 99.25, "minY": 197.0, "maxX": 281.0, "maxY": 389.0}, "class_id": 37, "box_caption": "gravy_rice 0.004", "scores": {"class_score": 0.003849029541015625}, "domain": "pixel"}, {"position": {"minX": 392.25, "minY": 212.125, "maxX": 511.25, "maxY": 301.5}, "class_id": 3, "box_caption": "schnitzel 0.004", "scores": {"class_score": 0.00374603271484375}, "domain": "pixel"}, {"position": {"minX": 377.25, "minY": 287.0, "maxX": 517.5, "maxY": 393.0}, "class_id": 12, "box_caption": "apples 0.003", "scores": {"class_score": 0.00348663330078125}, "domain": "pixel"}, {"position": {"minX": 377.25, "minY": 287.0, "maxX": 517.5, "maxY": 393.0}, "class_id": 16, "box_caption": "orange 0.003", "scores": {"class_score": 0.00341796875}, "domain": "pixel"}, {"position": {"minX": 374.75, "minY": 295.75, "maxX": 521.0, "maxY": 389.25}, "class_id": 13, "box_caption": "pesto_b\u00e9chamel_pasta_and_croissants 0.003", "scores": {"class_score": 0.0033206939697265625}, "domain": "pixel"}, {"position": {"minX": 438.0, "minY": 50.25, "maxX": 544.0, "maxY": 152.375}, "class_id": 37, "box_caption": "gravy_rice 0.003", "scores": {"class_score": 0.0031604766845703125}, "domain": "pixel"}, {"position": {"minX": 372.75, "minY": 204.875, "maxX": 531.0, "maxY": 314.0}, "class_id": 50, "box_caption": "pork_shank 0.003", "scores": {"class_score": 0.0028285980224609375}, "domain": "pixel"}, {"position": {"minX": 377.25, "minY": 287.0, "maxX": 517.5, "maxY": 393.0}, "class_id": 1, "box_caption": "tangerines 0.003", "scores": {"class_score": 0.0026149749755859375}, "domain": "pixel"}, {"position": {"minX": 376.75, "minY": 289.75, "maxX": 517.0, "maxY": 390.75}, "class_id": 33, "box_caption": "fennel_gratin 0.003", "scores": {"class_score": 0.002613067626953125}, "domain": "pixel"}, {"position": {"minX": 443.5, "minY": 49.375, "maxX": 541.0, "maxY": 146.375}, "class_id": 26, "box_caption": "mixed_salad 0.003", "scores": {"class_score": 0.0025615692138671875}, "domain": "pixel"}, {"position": {"minX": 376.75, "minY": 289.75, "maxX": 517.0, "maxY": 390.75}, "class_id": 53, "box_caption": "cauliflower 0.003", "scores": {"class_score": 0.0025615692138671875}, "domain": "pixel"}, {"position": {"minX": 376.0, "minY": 203.375, "maxX": 528.0, "maxY": 319.5}, "class_id": 48, "box_caption": "roast_veal 0.003", "scores": {"class_score": 0.0025310516357421875}, "domain": "pixel"}, {"position": {"minX": 81.0, "minY": 58.40625, "maxX": 185.25, "maxY": 166.125}, "class_id": 37, "box_caption": "gravy_rice 0.002", "scores": {"class_score": 0.0023517608642578125}, "domain": "pixel"}, {"position": {"minX": 83.875, "minY": 58.96875, "maxX": 180.375, "maxY": 169.75}, "class_id": 5, "box_caption": "yogurt 0.002", "scores": {"class_score": 0.002262115478515625}, "domain": "pixel"}, {"position": {"minX": 372.75, "minY": 211.5, "maxX": 530.0, "maxY": 310.0}, "class_id": 10, "box_caption": "pizza 0.002", "scores": {"class_score": 0.002208709716796875}, "domain": "pixel"}, {"position": {"minX": 376.75, "minY": 289.75, "maxX": 517.0, "maxY": 390.75}, "class_id": 9, "box_caption": "cutlets 0.002", "scores": {"class_score": 0.0021076202392578125}, "domain": "pixel"}, {"position": {"minX": 374.75, "minY": 295.75, "maxX": 521.0, "maxY": 389.25}, "class_id": 35, "box_caption": "pears 0.002", "scores": {"class_score": 0.0019931793212890625}, "domain": "pixel"}, {"position": {"minX": 375.0, "minY": 295.5, "maxX": 523.0, "maxY": 390.5}, "class_id": 69, "box_caption": "pineapple_cake 0.002", "scores": {"class_score": 0.0018701553344726562}, "domain": "pixel"}, {"position": {"minX": 375.25, "minY": 203.25, "maxX": 532.0, "maxY": 320.25}, "class_id": 56, "box_caption": "breaded_courgettes 0.002", "scores": {"class_score": 0.0018014907836914062}, "domain": "pixel"}, {"position": {"minX": 374.5, "minY": 207.0, "maxX": 529.0, "maxY": 314.0}, "class_id": 9, "box_caption": "cutlets 0.002", "scores": {"class_score": 0.0017566680908203125}, "domain": "pixel"}, {"position": {"minX": 441.25, "minY": 52.34375, "maxX": 543.5, "maxY": 148.125}, "class_id": 5, "box_caption": "yogurt 0.002", "scores": {"class_score": 0.0017366409301757812}, "domain": "pixel"}, {"position": {"minX": 84.25, "minY": 59.09375, "maxX": 179.75, "maxY": 169.875}, "class_id": 16, "box_caption": "orange 0.002", "scores": {"class_score": 0.0017023086547851562}, "domain": "pixel"}, {"position": {"minX": 376.75, "minY": 289.75, "maxX": 517.0, "maxY": 390.75}, "class_id": 28, "box_caption": "meatballs 0.002", "scores": {"class_score": 0.0016489028930664062}, "domain": "pixel"}, {"position": {"minX": 374.5, "minY": 294.5, "maxX": 520.0, "maxY": 387.0}, "class_id": 43, "box_caption": "salmon_(from_the_menu_it_looks_like_swordfish_actually) 0.002", "scores": {"class_score": 0.001605987548828125}, "domain": "pixel"}, {"position": {"minX": 373.25, "minY": 208.0, "maxX": 528.0, "maxY": 310.5}, "class_id": 67, "box_caption": "cream_soup_of_pumpkin_and_beans 0.002", "scores": {"class_score": 0.0015163421630859375}, "domain": "pixel"}, {"position": {"minX": 101.0, "minY": 197.5, "maxX": 278.0, "maxY": 393.0}, "class_id": 14, "box_caption": "lasagna_bolognese 0.001", "scores": {"class_score": 0.0014743804931640625}, "domain": "pixel"}, {"position": {"minX": 84.6875, "minY": 58.3125, "maxX": 181.0, "maxY": 170.5}, "class_id": 10, "box_caption": "pizza 0.001", "scores": {"class_score": 0.0014619827270507812}, "domain": "pixel"}, {"position": {"minX": 443.75, "minY": 50.6875, "maxX": 540.0, "maxY": 147.75}, "class_id": 17, "box_caption": "pasta_with_fish_sauce 0.001", "scores": {"class_score": 0.0013751983642578125}, "domain": "pixel"}, {"position": {"minX": 438.0, "minY": 50.25, "maxX": 544.0, "maxY": 152.375}, "class_id": 35, "box_caption": "pears 0.001", "scores": {"class_score": 0.0013360977172851562}, "domain": "pixel"}, {"position": {"minX": 396.0, "minY": 309.5, "maxX": 508.0, "maxY": 391.5}, "class_id": 4, "box_caption": "potatoes/purees 0.001", "scores": {"class_score": 0.0012807846069335938}, "domain": "pixel"}, {"position": {"minX": 371.25, "minY": 207.25, "maxX": 534.0, "maxY": 315.75}, "class_id": 58, "box_caption": "rosbeef 0.001", "scores": {"class_score": 0.0012683868408203125}, "domain": "pixel"}, {"position": {"minX": 443.75, "minY": 50.6875, "maxX": 540.0, "maxY": 147.75}, "class_id": 36, "box_caption": "tuna_pasta 0.001", "scores": {"class_score": 0.0011720657348632812}, "domain": "pixel"}, {"position": {"minX": 84.6875, "minY": 58.3125, "maxX": 181.0, "maxY": 170.5}, "class_id": 3, "box_caption": "schnitzel 0.001", "scores": {"class_score": 0.0011653900146484375}, "domain": "pixel"}, {"position": {"minX": 83.875, "minY": 56.4375, "maxX": 182.125, "maxY": 170.0}, "class_id": 21, "box_caption": "white_rice 0.001", "scores": {"class_score": 0.0011453628540039062}, "domain": "pixel"}, {"position": {"minX": 375.0, "minY": 295.5, "maxX": 523.0, "maxY": 390.5}, "class_id": 30, "box_caption": "bacon_and_courgette_pasta, 0.001", "scores": {"class_score": 0.0011262893676757812}, "domain": "pixel"}, {"position": {"minX": 97.9375, "minY": 203.5, "maxX": 281.0, "maxY": 394.5}, "class_id": 26, "box_caption": "mixed_salad 0.001", "scores": {"class_score": 0.00112152099609375}, "domain": "pixel"}, {"position": {"minX": 375.0, "minY": 213.0, "maxX": 530.5, "maxY": 308.5}, "class_id": 42, "box_caption": "savoury_pie_(Valle_dAosta_style) 0.001", "scores": {"class_score": 0.0011186599731445312}, "domain": "pixel"}, {"position": {"minX": 81.0, "minY": 58.46875, "maxX": 184.25, "maxY": 166.25}, "class_id": 7, "box_caption": "pudding 0.001", "scores": {"class_score": 0.0011043548583984375}, "domain": "pixel"}, {"position": {"minX": 384.5, "minY": 270.25, "maxX": 519.0, "maxY": 369.25}, "class_id": 4, "box_caption": "potatoes/purees 0.001", "scores": {"class_score": 0.0010538101196289062}, "domain": "pixel"}, {"position": {"minX": 443.5, "minY": 50.71875, "maxX": 540.0, "maxY": 148.875}, "class_id": 16, "box_caption": "orange 0.001", "scores": {"class_score": 0.001018524169921875}, "domain": "pixel"}], "class_labels": {"0": "bread", "1": "tangerines", "2": "carrots", "3": "schnitzel", "4": "potatoes/purees", "5": "yogurt", "6": "green_beans", "7": "pudding", "8": "spinach", "9": "cutlets", "10": "pizza", "11": "pasta_sugar_vegetarian", "12": "apples", "13": "pesto_b\u00e9chamel_pasta_and_croissants", "14": "lasagna_bolognese", "15": "moist_courgettes", "16": "orange", "17": "pasta_with_fish_sauce", "18": "chips", "19": "roast", "20": "pasta_mussels_and_clams", "21": "white_rice", "22": "spinach_and_ricotta_cheese_pie", "23": "meat_medallions", "24": "saffron_pasta_and_peas", "25": "potatoes/pure_ham", "26": "mixed_salad", "27": "pasta_mare_e_monti", "28": "meatballs", "29": "rustic_savoury_pie_(courgettes)", "30": "bacon_and_courgette_pasta,", "31": "ricotta_and_sausage_pasta", "32": "pizzoccheri", "33": "fennel_gratin", "34": "orecchiette_ragu", "35": "pears", "36": "tuna_pasta", "37": "gravy_rice", "38": "tuna_and_peas_pasta", "39": "peas", "40": "savoury_pie_3", "41": "bananas", "42": "savoury_pie_(Valle_dAosta_style)", "43": "salmon_(from_the_menu_it_looks_like_swordfish_actually)", "44": "calamari_guazzetto", "45": "fish_2_(fillet)", "46": "pasta_sauce", "47": "bruscitt", "48": "roast_veal", "49": "pasta_and_beans", "50": "pork_shank", "51": "Lombardy_soup", "52": "stewed_fennel", "53": "cauliflower", "54": "white_pasta", "55": "cod_with_olives", "56": "breaded_courgettes", "57": "fish_(fillet)", "58": "rosbeef", "59": "cream_cake_2", "60": "unidentified_white_food", "61": "roastbeef", "62": "cream_cake", "63": "Piedmontese_pastry", "64": "pasta_and_chickpeas", "65": "white_focaccia", "66": "soup", "67": "cream_soup_of_pumpkin_and_beans", "68": "chocolate_and_pear_cake", "69": "pineapple_cake", "70": "arugula", "71": "strudel"}}